crawler_tool/__init__.py
crawler_tool/bloomfilter.py
crawler_tool/dateTime.py
crawler_tool/fack_header.py
crawler_tool/pyEmail.py
crawler_tool/spider_tool.py
crawler_tool-0.2.2.dist-info/METADATA
crawler_tool-0.2.2.dist-info/WHEEL
crawler_tool-0.2.2.dist-info/top_level.txt
crawler_tool-0.2.2.dist-info/RECORD
